tpgUtils/.gitignore
tpgUtils/__init__.py
tpgUtils/__version__.py
tpgUtils/tpgPrint.py
tpgutils-0.1.4.dist-info/licenses/LICENSE
tpgutils-0.1.4.dist-info/METADATA
tpgutils-0.1.4.dist-info/WHEEL
tpgutils-0.1.4.dist-info/top_level.txt
tpgutils-0.1.4.dist-info/RECORD
