Metadata-Version: 2.4
Name: tpgUtils
Version: 0.1.4
Summary: shared application utlities.
Author-email: Criss Swaim <cswaim@tpginc.net>
Maintainer-email: Criss Swaim <cswaim@tpginc.net>
License-Expression: Apache-2.0
Project-URL: Homepage, https://example.com
Project-URL: Documentation, https://readthedocs.org
Project-URL: Repository, https://gitlab.com/tpgllc/tpgUtils
Project-URL: Issues, https://gitlab.com/tpgllc/tpgUtils/-/issues
Project-URL: Changelog, https://gitlab.com/tpgllc/tpgUtils/CHANGELOG.md
Keywords: app utils,print util
Classifier: Development Status :: 4 - Beta
Classifier: Programming Language :: Python :: 3.10
Classifier: Programming Language :: Python :: 3.11
Classifier: Programming Language :: Python :: 3.12
Classifier: Operating System :: OS Independent
Requires-Python: >=3.10
License-File: LICENSE
Requires-Dist: pytest
Provides-Extra: dev
Requires-Dist: build>=1.2.2; extra == "dev"
Requires-Dist: twine>=6.0.1; extra == "dev"
Requires-Dist: wheel>=0.45.1; extra == "dev"
Requires-Dist: packaging>=24.2; extra == "dev"
Requires-Dist: coverage; extra == "dev"
Requires-Dist: flake8; extra == "dev"
Requires-Dist: tox; extra == "dev"
Dynamic: license-file
